03-Design_Verification/3.02-Verilog_Testbenches/full_adder.sv
`timescale 1ns / 1ps

module full_adder (
    input  logic a,
    input  logic b,
    input  logic cin,
    output logic sum,
    output logic cout
);
    assign sum  = a ^ b ^ cin;
    assign cout = (a & b) | (b & cin) | (a & cin);
endmodule

03-Design_Verification/3.02-Verilog_Testbenches/full_adder_tb.sv
// full_adder_tb.sv
`timescale 1ns / 1ps

module full_adder_tb;

    // -------------------------------------------------------------------------
    // Signal declarations
    // Inputs to the DUT are driven by the testbench, so they're logic (reg)
    // Outputs from the DUT are read by the testbench, so they're logic (wire)
    // -------------------------------------------------------------------------
    logic a, b, cin;
    logic sum, cout;

    // -------------------------------------------------------------------------
    // DUT instantiation
    // -------------------------------------------------------------------------
    full_adder dut (
        .a    (a),
        .b    (b),
        .cin  (cin),
        .sum  (sum),
        .cout (cout)
    );

    // -------------------------------------------------------------------------
    // Stimulus and checking
    // -------------------------------------------------------------------------
    initial begin
        // Dump waveforms to a VCD file for GTKWave
        $dumpfile("full_adder.vcd");
        $dumpvars(0, full_adder_tb);

        $display("=== Full Adder Exhaustive Test ===");

        // Test all 8 input combinations
        // Format: {a, b, cin} -> expected {cout, sum}
        {a, b, cin} = 3'b000; #10;
        check(2'b00);

        {a, b, cin} = 3'b001; #10;
        check(2'b01);

        {a, b, cin} = 3'b010; #10;
        check(2'b01);

        {a, b, cin} = 3'b011; #10;
        check(2'b10);

        {a, b, cin} = 3'b100; #10;
        check(2'b01);

        {a, b, cin} = 3'b101; #10;
        check(2'b10);

        {a, b, cin} = 3'b110; #10;
        check(2'b10);

        {a, b, cin} = 3'b111; #10;
        check(2'b11);

        $display("=== Test Complete ===");
        $finish;
    end

    // -------------------------------------------------------------------------
    // Self-checking task
    // A task lets us reuse checking logic without repeating it 8 times
    // -------------------------------------------------------------------------
    task check(input logic [1:0] expected);
        // expected[1] = cout, expected[0] = sum
        if ({cout, sum} !== expected) begin
            $error("FAIL: a=%b b=%b cin=%b | got cout=%b sum=%b | expected cout=%b sum=%b",
                    a, b, cin, cout, sum, expected[1], expected[0]);
        end else begin
            $display("PASS: a=%b b=%b cin=%b | cout=%b sum=%b",
                      a, b, cin, cout, sum);
        end
    endtask

endmodule

03-Design_Verification/3.02-Verilog_Testbenches/full_adder.vcd
$date
	Sat Jun 27 21:35:10 2026
$end
$version
	Icarus Verilog
$end
$timescale
	1ps
$end
$scope module full_adder_tb $end
$var wire 1 ! sum $end
$var wire 1 " cout $end
$var reg 1 # a $end
$var reg 1 $ b $end
$var reg 1 % cin $end
$scope module dut $end
$var wire 1 # a $end
$var wire 1 $ b $end
$var wire 1 % cin $end
$var wire 1 " cout $end
$var wire 1 ! sum $end
$upscope $end
$scope task check $end
$var reg 2 & expected [1:0] $end
$upscope $end
$upscope $end
$enddefinitions $end
$comment Show the parameter values. $end
$dumpall
$end
#0
$dumpvars
bx &
0%
0$
0#
0"
0!
$end
#10000
1!
1%
b0 &
#20000
1!
1$
0%
b1 &
#30000
1"
0!
1%
#40000
0"
1!
1#
0$
0%
b10 &
#50000
1"
0!
1%
b1 &
#60000
1"
0!
1$
0%
b10 &
#70000
1!
1%
#80000
b11 &
